wdplot/__init__.py
wdplot/bivariate.py
wdplot/image.py
wdplot/prep.py
wdplot/truevspred.py
wdplot-0.0.1.dist-info/LICENSE
wdplot-0.0.1.dist-info/METADATA
wdplot-0.0.1.dist-info/WHEEL
wdplot-0.0.1.dist-info/top_level.txt
wdplot-0.0.1.dist-info/RECORD
