Metadata-Version: 2.1
Name: wdplot
Version: 0.0.1
Summary: Various plotting tools on top of matplotlib.
Home-page: https://github.com/wdobbels/wdplot
Author: Wouter Dobbels
Author-email: dobbelswouter@gmail.com
License: UNKNOWN
Platform: UNKNOWN
Classifier: Programming Language :: Python :: 3
Classifier: License :: OSI Approved :: MIT License
Classifier: Operating System :: OS Independent
Requires-Python: >=3.6
